{
    "info": {
        "description": null,
        "url": null,
        "version": null,
        "year": 2022,
        "contributor": null,
        "date_created": "2022-07-27 14:22:40.556014"
    },
    "licenses": [
        {
            "url": null,
            "id": 0,
            "name": null
        }
    ],
    "images": [
        {
            "license": 0,
            "url": null,
            "file_name": "JPEGImages/00648.jpg",
            "height": 800,
            "width": 1200,
            "date_captured": null,
            "id": 47
        }
    ],
    "categories": [
        {
            "supercategory": null,
            "id": 0,
            "name": "_background_"
        },
        {
            "supercategory": null,
            "id": 1,
            "name": "pothole"
        }
    ],
    "annotations": [
        {
            "id": 73,
            "image_id": 47,
            "category_id": 1,
            "segmentation": [
                [
                    712.728813559322,
                    740.5254237288136,
                    691.542372881356,
                    757.4745762711865,
                    689.8474576271187,
                    767.6440677966102,
                    693.2372881355933,
                    781.2033898305085,
                    716.1186440677966,
                    779.5084745762713,
                    728.8305084745763,
                    780.3559322033899,
                    762.7288135593221,
                    780.3559322033899,
                    767.8135593220339,
                    782.0508474576271,
                    796.6271186440679,
                    782.8983050847459,
                    811.0338983050848,
                    781.2033898305085,
                    827.135593220339,
                    780.3559322033899,
                    838.1525423728814,
                    773.5762711864407,
                    865.271186440678,
                    775.271186440678,
                    885.6101694915254,
                    765.9491525423729,
                    890.6949152542373,
                    765.9491525423729,
                    905.1016949152543,
                    765.9491525423729,
                    912.7288135593221,
                    763.406779661017,
                    920.3559322033899,
                    755.7796610169491,
                    921.2033898305085,
                    749.8474576271187,
                    921.2033898305085,
                    743.9152542372882,
                    911.8813559322034,
                    737.135593220339,
                    893.2372881355933,
                    732.8983050847459,
                    882.2203389830509,
                    732.8983050847459,
                    873.7457627118645,
                    731.2033898305085,
                    866.1186440677967,
                    727.8135593220339,
                    844.0847457627119,
                    726.9661016949153,
                    831.3728813559322,
                    726.9661016949153,
                    818.6610169491526,
                    727.8135593220339,
                    802.5593220338983,
                    730.3559322033899,
                    790.6949152542373,
                    732.0508474576271
                ]
            ],
            "area": 9822.0,
            "bbox": [
                689.0,
                726.0,
                233.0,
                57.0
            ],
            "iscrowd": 0
        },
        {
            "id": 74,
            "image_id": 47,
            "category_id": 1,
            "segmentation": [
                [
                    445.7796610169492,
                    510.86440677966107,
                    455.10169491525426,
                    526.1186440677966,
                    470.3559322033899,
                    526.1186440677966,
                    494.93220338983053,
                    526.9661016949153,
                    501.7118644067797,
                    528.6610169491526,
                    518.6610169491526,
                    532.0508474576271,
                    539.0,
                    535.4406779661017,
                    554.2542372881356,
                    535.4406779661017,
                    582.2203389830509,
                    535.4406779661017,
                    590.6949152542373,
                    535.4406779661017,
                    613.5762711864407,
                    536.2881355932203,
                    628.8305084745763,
                    536.2881355932203,
                    634.7627118644068,
                    535.4406779661017,
                    654.2542372881356,
                    526.9661016949153,
                    670.3559322033899,
                    517.6440677966102,
                    677.135593220339,
                    517.6440677966102,
                    685.6101694915254,
                    507.4745762711865,
                    686.4576271186442,
                    500.6949152542373,
                    677.9830508474577,
                    494.7627118644068,
                    660.1864406779662,
                    490.52542372881356,
                    649.1694915254237,
                    489.67796610169495,
                    633.9152542372882,
                    490.52542372881356,
                    620.3559322033899,
                    493.0677966101695,
                    602.5593220338983,
                    490.52542372881356,
                    571.2033898305085,
                    489.67796610169495,
                    549.1694915254237,
                    492.22033898305085,
                    529.6779661016949,
                    492.22033898305085,
                    511.8813559322034,
                    496.4576271186441,
                    504.25423728813564,
                    497.3050847457627,
                    490.69491525423734,
                    499.8474576271187,
                    479.6779661016949,
                    503.23728813559325,
                    468.66101694915255,
                    504.0847457627119
                ]
            ],
            "area": 8590.0,
            "bbox": [
                445.0,
                489.0,
                242.0,
                48.0
            ],
            "iscrowd": 0
        },
        {
            "id": 75,
            "image_id": 47,
            "category_id": 1,
            "segmentation": [
                [
                    827.135593220339,
                    495.6101694915254,
                    836.4576271186442,
                    504.93220338983053,
                    852.5593220338983,
                    508.3220338983051,
                    863.5762711864407,
                    508.3220338983051,
                    873.7457627118645,
                    507.4745762711865,
                    881.3728813559322,
                    505.7796610169492,
                    888.1525423728814,
                    504.0847457627119,
                    897.4745762711865,
                    504.0847457627119,
                    918.6610169491526,
                    508.3220338983051,
                    923.7457627118645,
                    507.4745762711865,
                    933.0677966101696,
                    504.93220338983053,
                    939.0,
                    503.23728813559325,
                    939.0,
                    493.91525423728814,
                    935.6101694915254,
                    488.8305084745763,
                    930.5254237288136,
                    485.4406779661017,
                    923.7457627118645,
                    482.8983050847458,
                    916.1186440677967,
                    482.0508474576271,
                    907.6440677966102,
                    481.2033898305085,
                    895.7796610169491,
                    486.2881355932204,
                    888.1525423728814,
                    487.135593220339,
                    879.677966101695,
                    487.135593220339,
                    873.7457627118645,
                    489.67796610169495,
                    866.9661016949153,
                    489.67796610169495,
                    852.5593220338983,
                    498.1525423728814
                ]
            ],
            "area": 1916.0,
            "bbox": [
                827.0,
                481.0,
                113.0,
                28.0
            ],
            "iscrowd": 0
        }
    ]
}